CHANGELOG.md
pytimetools/__init__.py
pytimetools/fmttools.py
pytimetools/gmttools.py
pytimetools/localtools.py
pytimetools/timestamptools.py
pytimetools/tools.py
pytimetools/tztools.py
pytimetools/utctools.py
pytimetools-0.1.3.9.dist-info/LICENSE
pytimetools-0.1.3.9.dist-info/WHEEL
pytimetools-0.1.3.9.dist-info/METADATA
pytimetools-0.1.3.9.dist-info/RECORD
