Metadata-Version: 2.1
Name: pytimetools
Version: 0.1.3.9
Summary: a time tools for django
Home-page: https://github.com/pydtools/pytimetools/
Author: huoyinghui
Author-email: hyhlinux@163.com
Requires-Python: >=2.7, !=3.0.*, !=3.1.*, !=3.2.*, !=3.3.*, !=3.4.*
Classifier: Programming Language :: Python :: 2
Classifier: Programming Language :: Python :: 2.7
Classifier: Programming Language :: Python :: 3
Classifier: Programming Language :: Python :: 3.5
Classifier: Programming Language :: Python :: 3.6
Classifier: Programming Language :: Python :: 3.7
Classifier: Programming Language :: Python :: 3.8
Classifier: Programming Language :: Python :: 3.9
Requires-Dist: pytz (>=2019.2,<2020.0)
Project-URL: Bug Tracker, https://github.com/pydtools/pytimetools/issues
Project-URL: Documentation, https://github.com/pydtools/pytimetools/wiki
Project-URL: Repository, https://github.com/pydtools/pytimetools/
Project-URL: github, https://github.com/pydtools/pytimetools/
